README.md
setup.py
PETGoldstandardBaselinesVisualizers.egg-info/PKG-INFO
PETGoldstandardBaselinesVisualizers.egg-info/SOURCES.txt
PETGoldstandardBaselinesVisualizers.egg-info/dependency_links.txt
PETGoldstandardBaselinesVisualizers.egg-info/requires.txt
PETGoldstandardBaselinesVisualizers.egg-info/top_level.txt
Visualizers/BaselinePredictorAgreementInterface.py
Visualizers/BaselinesComparisonLineView.py
Visualizers/CalculateBaselinePredictorsAgreement.py
Visualizers/Colors.py
Visualizers/__init__.py