Metadata-Version: 2.1
Name: PETGoldstandardBaselinesVisualizers
Version: 1.0.2
Summary: Visualizers of the PET dataset goldstandard data and baselines prediction
Home-page: https://huggingface.co/datasets/patriziobellan/PET
Author: Patrizio Bellan
Author-email: patrizio.bellan@gmail.com
License: MIT
